django_mailbox/__init__.py
django_mailbox/admin.py
django_mailbox/apps.py
django_mailbox/google_utils.py
django_mailbox/models.py
django_mailbox/signals.py
django_mailbox/utils.py
django_mailbox/locale/ru_RU/LC_MESSAGES/django.mo
django_mailbox/locale/ru_RU/LC_MESSAGES/django.po
django_mailbox/management/__init__.py
django_mailbox/management/commands/__init__.py
django_mailbox/management/commands/getmail.py
django_mailbox/management/commands/processincomingmessage.py
django_mailbox/management/commands/rebuildmessageattachments.py
django_mailbox/migrations/0001_initial.py
django_mailbox/migrations/__init__.py
django_mailbox/transports/__init__.py
django_mailbox/transports/babyl.py
django_mailbox/transports/base.py
django_mailbox/transports/generic.py
django_mailbox/transports/gmail.py
django_mailbox/transports/imap.py
django_mailbox/transports/maildir.py
django_mailbox/transports/mbox.py
django_mailbox/transports/mh.py
django_mailbox/transports/mmdf.py
django_mailbox/transports/pop3.py
tests/__init__.py
tests/base.py
tests/test_integration_imap.py
tests/test_mailbox.py
tests/test_message_flattening.py
tests/test_process_email.py
tests/test_processincomingmessage.py
tests/test_transports.py
django_mailbox_dynamic-5.0.0.dist-info/LICENSE
django_mailbox_dynamic-5.0.0.dist-info/METADATA
django_mailbox_dynamic-5.0.0.dist-info/WHEEL
django_mailbox_dynamic-5.0.0.dist-info/top_level.txt
django_mailbox_dynamic-5.0.0.dist-info/RECORD
